s3_locks/__init__.py
s3_locks/main.py
s3_locks/py.typed
s3_locks-0.1.0.dist-info/WHEEL
s3_locks-0.1.0.dist-info/METADATA
s3_locks-0.1.0.dist-info/RECORD
